flask33/__init__.py
flask33/__main__.py
flask33/app.py
flask33/blueprints.py
flask33/cli.py
flask33/config.py
flask33/ctx.py
flask33/debughelpers.py
flask33/globals.py
flask33/helpers.py
flask33/json/__init__.py
flask33/json/__pycache__/__init__.cpython-312.pyc
flask33/json/__pycache__/provider.cpython-312.pyc
flask33/json/__pycache__/tag.cpython-312.pyc
flask33/json/provider.py
flask33/json/tag.py
flask33/logging.py
flask33/py.typed
flask33/sansio/__init__.py
flask33/sansio/__pycache__/__init__.cpython-312.pyc
flask33/sansio/__pycache__/app.cpython-312.pyc
flask33/sansio/__pycache__/blueprints.cpython-312.pyc
flask33/sansio/__pycache__/scaffold.cpython-312.pyc
flask33/sansio/app.py
flask33/sansio/blueprints.py
flask33/sansio/README.md
flask33/sansio/scaffold.py
flask33/sessions.py
flask33/signals.py
flask33/templating.py
flask33/testing.py
flask33/typing.py
flask33/views.py
flask33/wrappers.py
flask33-0.1.0.dist-info/LICENSE
flask33-0.1.0.dist-info/METADATA
flask33-0.1.0.dist-info/WHEEL
flask33-0.1.0.dist-info/RECORD
